valueguard/__init__.py
valueguard/valueguard.py
valueguard-0.2.0.dist-info/METADATA
valueguard-0.2.0.dist-info/WHEEL
valueguard-0.2.0.dist-info/top_level.txt
valueguard-0.2.0.dist-info/RECORD
