Metadata-Version: 2.1
Name: valueguard
Version: 0.2.0
Summary: The official client for the Valueguard API
Home-page: https://github.com/Valueguard-Index-Sweden/valueguard-python-client
Author: Valueguard
Author-email: info@valueguard.se
License: MIT
Platform: UNKNOWN
Classifier: Programming Language :: Python :: 3.7
Requires-Dist: requests (>=2)
